README.txt
setup.py
docs/HISTORY.txt
docs/INSTALL.txt
docs/LICENSE.GPL
docs/LICENSE.txt
plone/__init__.py
plone.app.memberschema.egg-info/PKG-INFO
plone.app.memberschema.egg-info/SOURCES.txt
plone.app.memberschema.egg-info/dependency_links.txt
plone.app.memberschema.egg-info/entry_points.txt
plone.app.memberschema.egg-info/namespace_packages.txt
plone.app.memberschema.egg-info/not-zip-safe
plone.app.memberschema.egg-info/requires.txt
plone.app.memberschema.egg-info/top_level.txt
plone/app/__init__.py
plone/app/memberschema/TODO.txt
plone/app/memberschema/__init__.py
plone/app/memberschema/bag.py
plone/app/memberschema/configure.zcml
plone/app/memberschema/default.py
plone/app/memberschema/interfaces.py
plone/app/memberschema/plugin.py
plone/app/memberschema/portrait.py
plone/app/memberschema/profiles.zcml
plone/app/memberschema/utils.py
plone/app/memberschema/browser/__init__.py
plone/app/memberschema/browser/configure.zcml
plone/app/memberschema/browser/datamanager.py
plone/app/memberschema/browser/edit.py
plone/app/memberschema/browser/plugin.zpt
plone/app/memberschema/browser/portrait.py
plone/app/memberschema/exportimport/__init__.py
plone/app/memberschema/exportimport/configure.zcml
plone/app/memberschema/exportimport/handler.py
plone/app/memberschema/exportimport/installation.py
plone/app/memberschema/profiles/default/memberschema.xml
plone/app/memberschema/profiles/default/metadata.xml
plone/app/memberschema/profiles/default/plone.app.memberschema_various.txt
plone/app/memberschema/tests/__init__.py
plone/app/memberschema/tests/common.py
plone/app/memberschema/tests/test_datamanager.py
plone/app/memberschema/tests/test_exportimport.py
plone/app/memberschema/tests/test_plugin.py
plone/app/memberschema/tests/zptlogo.gif