Metadata-Version: 1.0
Name: plone.app.memberschema
Version: 1.0a3
Summary: Support for storing member data based on interfaces
Home-page: http://pypi.python.org/pypi/plone.app.memberschema
Author: Martin Aspeli
Author-email: optilude@gmail.com
License: GPL
Keywords: plone zope pas member schema interface
Platform: UNKNOWN
Classifier: Framework :: Plone
Classifier: Programming Language :: Python
Classifier: Topic :: Software Development :: Libraries :: Python Modules
